pyfost/ns/__about__.py
pyfost/ns/__init__.py
pyfost-0.0.2.dist-info/METADATA
pyfost-0.0.2.dist-info/WHEEL
pyfost-0.0.2.dist-info/licenses/LICENSE.txt
pyfost-0.0.2.dist-info/RECORD
